gcp_python_logging/__init__.py
gcp_python_logging/gcp_logging.py
gcp_python_logging/logging.py
gcp_python_logging-1.1.1.dist-info/LICENSE
gcp_python_logging-1.1.1.dist-info/METADATA
gcp_python_logging-1.1.1.dist-info/WHEEL
gcp_python_logging-1.1.1.dist-info/top_level.txt
gcp_python_logging-1.1.1.dist-info/RECORD
