Metadata-Version: 2.1
Name: gcp-python-logging
Version: 1.1.1
Summary: A python module for the handy printing of logs to StackDriver based on severity
Home-page: https://github.com/hawesdb/gcp-python-logging
Author: Daniel Hawes
Author-email: hawesdb@gmail.com
License: UNKNOWN
Platform: UNKNOWN
Classifier: Programming Language :: Python :: 3
Classifier: License :: OSI Approved :: MIT License
Classifier: Operating System :: OS Independent
Requires-Python: >=3.7
Requires-Dist: google-cloud-logging
Requires-Dist: protobuf
